shelly/__init__.py
shelly/shelly_control.py
shelly/shelly_control_old.py
shelly_control-0.3.dist-info/LICENSE
shelly_control-0.3.dist-info/METADATA
shelly_control-0.3.dist-info/WHEEL
shelly_control-0.3.dist-info/top_level.txt
shelly_control-0.3.dist-info/RECORD
