Metadata-Version: 2.1
Name: shelly_control
Version: 0.3
Summary: A python package for Shelly Cloud API. Shelly is devoted to the development of innovative IoT solutions and products.
Author-email: Ankush Kumar <ankush1611996@gmail.com>
Project-URL: Homepage, https://github.com/AnkushRozra/shelly
Project-URL: Bug Tracker, https://github.com/AnkushRozra/shelly/issues
Keywords: Shelly,Shelly plug,Shelly cloud api,shelly cloud,Shelly access control,Shelly python library
Classifier: Programming Language :: Python :: 3
Classifier: License :: OSI Approved :: MIT License
Classifier: Operating System :: OS Independent
Requires-Python: >=3.8
License-File: LICENSE
Requires-Dist: requests
